rolfsen/__init__.py
rolfsen-0.0.2.dist-info/METADATA
rolfsen-0.0.2.dist-info/WHEEL
rolfsen-0.0.2.dist-info/top_level.txt
rolfsen-0.0.2.dist-info/RECORD
